<?xml version="1.0" encoding="utf-8"?>
<Dependencies>
  <Dependency>
    <ExtensionId>CKEditor</ExtensionId>
    <LoaderName>DynamicExtensionLoader</LoaderName>
    <VirtualPath>~/Modules/CKEditor/CKEditor.csproj</VirtualPath>
    <Hash>cf6aa5e01c1b44fd</Hash>
  </Dependency>
  <Dependency>
    <ExtensionId>CyberStride.Contacts</ExtensionId>
    <LoaderName>DynamicExtensionLoader</LoaderName>
    <VirtualPath>~/Modules/CyberStride.Contacts/CyberStride.Contacts.csproj</VirtualPath>
    <Hash>f950d75b03740107</Hash>
  </Dependency>
  <Dependency>
    <ExtensionId>Markdown</ExtensionId>
    <LoaderName>PrecompiledExtensionLoader</LoaderName>
    <VirtualPath>~/Modules/Markdown/bin/Markdown.dll</VirtualPath>
    <Hash>923a1426e8e85b7b</Hash>
  </Dependency>
  <Dependency>
    <ExtensionId>Orchard.Alias</ExtensionId>
    <LoaderName>PrecompiledExtensionLoader</LoaderName>
    <VirtualPath>~/Modules/Orchard.Alias/bin/Orchard.Alias.dll</VirtualPath>
    <Hash>48f859a6d503d620</Hash>
  </Dependency>
  <Dependency>
    <ExtensionId>Orchard.Autoroute</ExtensionId>
    <LoaderName>PrecompiledExtensionLoader</LoaderName>
    <VirtualPath>~/Modules/Orchard.Autoroute/bin/Orchard.Autoroute.dll</VirtualPath>
    <Hash>dba4cdb07f5c96e2</Hash>
  </Dependency>
  <Dependency>
    <ExtensionId>Orchard.Blogs</ExtensionId>
    <LoaderName>PrecompiledExtensionLoader</LoaderName>
    <VirtualPath>~/Modules/Orchard.Blogs/bin/Orchard.Blogs.dll</VirtualPath>
    <Hash>48f8c1a735e9c82d</Hash>
  </Dependency>
  <Dependency>
    <ExtensionId>Orchard.Comments</ExtensionId>
    <LoaderName>PrecompiledExtensionLoader</LoaderName>
    <VirtualPath>~/Modules/Orchard.Comments/bin/Orchard.Comments.dll</VirtualPath>
    <Hash>9258844551fbca49</Hash>
  </Dependency>
  <Dependency>
    <ExtensionId>Orchard.ContentPicker</ExtensionId>
    <LoaderName>PrecompiledExtensionLoader</LoaderName>
    <VirtualPath>~/Modules/Orchard.ContentPicker/bin/Orchard.ContentPicker.dll</VirtualPath>
    <Hash>4913d1c252d5338f</Hash>
  </Dependency>
  <Dependency>
    <ExtensionId>Orchard.ContentTypes</ExtensionId>
    <LoaderName>PrecompiledExtensionLoader</LoaderName>
    <VirtualPath>~/Modules/Orchard.ContentTypes/bin/Orchard.ContentTypes.dll</VirtualPath>
    <Hash>926203bf0a23ff6f</Hash>
  </Dependency>
  <Dependency>
    <ExtensionId>Orchard.Email</ExtensionId>
    <LoaderName>DynamicExtensionLoader</LoaderName>
    <VirtualPath>~/Modules/Orchard.Email/Orchard.Email.csproj</VirtualPath>
    <Hash>69e90cd7fbd56702</Hash>
  </Dependency>
  <Dependency>
    <ExtensionId>Orchard.Fields</ExtensionId>
    <LoaderName>PrecompiledExtensionLoader</LoaderName>
    <VirtualPath>~/Modules/Orchard.Fields/bin/Orchard.Fields.dll</VirtualPath>
    <Hash>db885f2c49d59d55</Hash>
  </Dependency>
  <Dependency>
    <ExtensionId>Orchard.Forms</ExtensionId>
    <LoaderName>PrecompiledExtensionLoader</LoaderName>
    <VirtualPath>~/Modules/Orchard.Forms/bin/Orchard.Forms.dll</VirtualPath>
    <Hash>48f941a7babe7c3d</Hash>
  </Dependency>
  <Dependency>
    <ExtensionId>Orchard.jQuery</ExtensionId>
    <LoaderName>PrecompiledExtensionLoader</LoaderName>
    <VirtualPath>~/Modules/Orchard.jQuery/bin/Orchard.jQuery.dll</VirtualPath>
    <Hash>48fd09ab7fa3f5b6</Hash>
  </Dependency>
  <Dependency>
    <ExtensionId>Orchard.Media</ExtensionId>
    <LoaderName>PrecompiledExtensionLoader</LoaderName>
    <VirtualPath>~/Modules/Orchard.Media/bin/Orchard.Media.dll</VirtualPath>
    <Hash>92385d2dacd7a73b</Hash>
  </Dependency>
  <Dependency>
    <ExtensionId>Orchard.MediaPicker</ExtensionId>
    <LoaderName>PrecompiledExtensionLoader</LoaderName>
    <VirtualPath>~/Modules/Orchard.MediaPicker/bin/Orchard.MediaPicker.dll</VirtualPath>
    <Hash>db98973c8049185c</Hash>
  </Dependency>
  <Dependency>
    <ExtensionId>Orchard.Modules</ExtensionId>
    <LoaderName>PrecompiledExtensionLoader</LoaderName>
    <VirtualPath>~/Modules/Orchard.Modules/bin/Orchard.Modules.dll</VirtualPath>
    <Hash>48ffd1ae4207150f</Hash>
  </Dependency>
  <Dependency>
    <ExtensionId>Orchard.Packaging</ExtensionId>
    <LoaderName>PrecompiledExtensionLoader</LoaderName>
    <VirtualPath>~/Modules/Orchard.Packaging/bin/Orchard.Packaging.dll</VirtualPath>
    <Hash>925943b644474a57</Hash>
  </Dependency>
  <Dependency>
    <ExtensionId>Orchard.Pages</ExtensionId>
    <LoaderName>PrecompiledExtensionLoader</LoaderName>
    <VirtualPath>~/Modules/Orchard.Pages/bin/Orchard.Pages.dll</VirtualPath>
    <Hash>48f889a701764f26</Hash>
  </Dependency>
  <Dependency>
    <ExtensionId>Orchard.Projections</ExtensionId>
    <LoaderName>PrecompiledExtensionLoader</LoaderName>
    <VirtualPath>~/Modules/Orchard.Projections/bin/Orchard.Projections.dll</VirtualPath>
    <Hash>dbabf5b7a37ce3c7</Hash>
  </Dependency>
  <Dependency>
    <ExtensionId>Orchard.PublishLater</ExtensionId>
    <LoaderName>PrecompiledExtensionLoader</LoaderName>
    <VirtualPath>~/Modules/Orchard.PublishLater/bin/Orchard.PublishLater.dll</VirtualPath>
    <Hash>491081befb442525</Hash>
  </Dependency>
  <Dependency>
    <ExtensionId>Orchard.Recipes</ExtensionId>
    <LoaderName>PrecompiledExtensionLoader</LoaderName>
    <VirtualPath>~/Modules/Orchard.Recipes/bin/Orchard.Recipes.dll</VirtualPath>
    <Hash>24fd5fb77eeeb30e</Hash>
  </Dependency>
  <Dependency>
    <ExtensionId>Orchard.Roles</ExtensionId>
    <LoaderName>PrecompiledExtensionLoader</LoaderName>
    <VirtualPath>~/Modules/Orchard.Roles/bin/Orchard.Roles.dll</VirtualPath>
    <Hash>48f931a7a264413b</Hash>
  </Dependency>
  <Dependency>
    <ExtensionId>Orchard.Rules</ExtensionId>
    <LoaderName>PrecompiledExtensionLoader</LoaderName>
    <VirtualPath>~/Modules/Orchard.Rules/bin/Orchard.Rules.dll</VirtualPath>
    <Hash>24f2afaceb6616b8</Hash>
  </Dependency>
  <Dependency>
    <ExtensionId>Orchard.Scripting</ExtensionId>
    <LoaderName>PrecompiledExtensionLoader</LoaderName>
    <VirtualPath>~/Modules/Orchard.Scripting/bin/Orchard.Scripting.dll</VirtualPath>
    <Hash>4906a1b5141242e9</Hash>
  </Dependency>
  <Dependency>
    <ExtensionId>Orchard.Setup</ExtensionId>
    <LoaderName>PrecompiledExtensionLoader</LoaderName>
    <VirtualPath>~/Modules/Orchard.Setup/bin/Orchard.Setup.dll</VirtualPath>
    <Hash>6e4b31b3e0ec13e2</Hash>
  </Dependency>
  <Dependency>
    <ExtensionId>Orchard.Tags</ExtensionId>
    <LoaderName>PrecompiledExtensionLoader</LoaderName>
    <VirtualPath>~/Modules/Orchard.Tags/bin/Orchard.Tags.dll</VirtualPath>
    <Hash>48f581a3f31f6dc5</Hash>
  </Dependency>
  <Dependency>
    <ExtensionId>Orchard.Themes</ExtensionId>
    <LoaderName>PrecompiledExtensionLoader</LoaderName>
    <VirtualPath>~/Modules/Orchard.Themes/bin/Orchard.Themes.dll</VirtualPath>
    <Hash>48fc39aaa994149c</Hash>
  </Dependency>
  <Dependency>
    <ExtensionId>Orchard.Tokens</ExtensionId>
    <LoaderName>PrecompiledExtensionLoader</LoaderName>
    <VirtualPath>~/Modules/Orchard.Tokens/bin/Orchard.Tokens.dll</VirtualPath>
    <Hash>48fca9ab232b7caa</Hash>
  </Dependency>
  <Dependency>
    <ExtensionId>Orchard.Users</ExtensionId>
    <LoaderName>PrecompiledExtensionLoader</LoaderName>
    <VirtualPath>~/Modules/Orchard.Users/bin/Orchard.Users.dll</VirtualPath>
    <Hash>48f999a806ddba48</Hash>
  </Dependency>
  <Dependency>
    <ExtensionId>Orchard.Warmup</ExtensionId>
    <LoaderName>PrecompiledExtensionLoader</LoaderName>
    <VirtualPath>~/Modules/Orchard.Warmup/bin/Orchard.Warmup.dll</VirtualPath>
    <Hash>48fce9ab5c0c6eb2</Hash>
  </Dependency>
  <Dependency>
    <ExtensionId>Orchard.Widgets</ExtensionId>
    <LoaderName>PrecompiledExtensionLoader</LoaderName>
    <VirtualPath>~/Modules/Orchard.Widgets/bin/Orchard.Widgets.dll</VirtualPath>
    <Hash>dbab1db6b12805ac</Hash>
  </Dependency>
  <Dependency>
    <ExtensionId>SysCache</ExtensionId>
    <LoaderName>PrecompiledExtensionLoader</LoaderName>
    <VirtualPath>~/Modules/SysCache/bin/SysCache.dll</VirtualPath>
    <Hash>92611556796df552</Hash>
  </Dependency>
  <Dependency>
    <ExtensionId>TinyMce</ExtensionId>
    <LoaderName>PrecompiledExtensionLoader</LoaderName>
    <VirtualPath>~/Modules/TinyMce/bin/TinyMce.dll</VirtualPath>
    <Hash>48e74995bbbac5fe</Hash>
  </Dependency>
  <Dependency>
    <ExtensionId>UpgradeTo16</ExtensionId>
    <LoaderName>PrecompiledExtensionLoader</LoaderName>
    <VirtualPath>~/Modules/UpgradeTo16/bin/UpgradeTo16.dll</VirtualPath>
    <Hash>e97daf7e1c0adf</Hash>
  </Dependency>
  <Dependency>
    <ExtensionId>Vandelay.TranslationManager</ExtensionId>
    <LoaderName>DynamicExtensionLoader</LoaderName>
    <VirtualPath>~/Modules/Vandelay.TranslationManager/Vandelay.TranslationManager.csproj</VirtualPath>
    <Hash>d9d4e2b71202579c</Hash>
  </Dependency>
</Dependencies>